[
    {
        "head":{
            "title" : "Free",
            "price":"0",
            "period":"month"
        },
        "features":[
            {
                "title" : "Single User",
                "avaiable" : true
            },
            {
                "title" : "5GB Storage",
                "avaiable" : true
            },
            {
                "title" : "Unlimited Public Projects",
                "avaiable" : true
            },
            {
                "title" : "Community Access",
                "avaiable" : true
            },
            {
                "title" : "Unlimited Private Projects",
                "avaiable" : false
            },
            {
                "title" : "Dedicated Phone Support",
                "avaiable" : false
            },
            {
                "title" : "Free Subdomain",
                "avaiable" : false
            },
            {
                "title" : "Monthly Status Reports",
                "avaiable" : false
            }
        ],
        "button" : "#"
    },

    {
    "head":{
        "title" : "Plus",
        "price":"9",
        "period":"month"
    },
    "features":[
        {
            "title" : "5 Users",
            "avaiable" : true
        },
        {
            "title" : "50GB Storage",
            "avaiable" : true
        },
        {
            "title" : "Unlimited Public Projects",
            "avaiable" : true
        },
        {
            "title" : "Community Access",
            "avaiable" : true
        },
        {
            "title" : "Unlimited Private Projects",
            "avaiable" : true
        },
        {
            "title" : "Dedicated Phone Support",
            "avaiable" : true
        },
        {
            "title" : "Free Subdomain",
            "avaiable" : true
        },
        {
            "title" : "Monthly Status Reports",
            "avaiable" : false
        }
    ],
    "button" : "#"
    },
    {
    "head":{
        "title" : "Pro",
        "price":"49",
        "period":"month"
    },
    "features":[
        {
            "title" : "Unlimited Users",
            "avaiable" : true
        },
        {
            "title" : "150GB Storage",
            "avaiable" : true
        },
        {
            "title" : "Unlimited Public Projects",
            "avaiable" : true
        },
        {
            "title" : "Community Access",
            "avaiable" : true
        },
        {
            "title" : "Unlimited Private Projects",
            "avaiable" : true
        },
        {
            "title" : "Dedicated Phone Support",
            "avaiable" : true
        },
        {
            "title" : "Unlimited Free Subdomain",
            "avaiable" : true
        },
        {
            "title" : "Monthly Status Reports",
            "avaiable" : true
        }
    ],
    "button" : "https://www.google.com"
    }
]